teachbooks_sphinx_grasple/__init__.py
teachbooks_sphinx_grasple/directive.py
teachbooks_sphinx_grasple/latex.py
teachbooks_sphinx_grasple/nodes.py
teachbooks_sphinx_grasple/post_transforms.py
teachbooks_sphinx_grasple/transforms.py
teachbooks_sphinx_grasple/utils.py
teachbooks_sphinx_grasple/assets/html/grasple-exercise.css
teachbooks_sphinx_grasple/assets/html/grasple-exercise.js
teachbooks_sphinx_grasple/translations/README.md
teachbooks_sphinx_grasple/translations/_convert.py
teachbooks_sphinx_grasple/translations/jsons/Click.json
teachbooks_sphinx_grasple/translations/jsons/Grasple Exercise.json
teachbooks_sphinx_grasple/translations/locales/ar/LC_MESSAGES/grasple.mo
teachbooks_sphinx_grasple/translations/locales/ar/LC_MESSAGES/grasple.po
teachbooks_sphinx_grasple/translations/locales/bn/LC_MESSAGES/grasple.mo
teachbooks_sphinx_grasple/translations/locales/bn/LC_MESSAGES/grasple.po
teachbooks_sphinx_grasple/translations/locales/cs/LC_MESSAGES/grasple.mo
teachbooks_sphinx_grasple/translations/locales/cs/LC_MESSAGES/grasple.po
teachbooks_sphinx_grasple/translations/locales/de/LC_MESSAGES/grasple.mo
teachbooks_sphinx_grasple/translations/locales/de/LC_MESSAGES/grasple.po
teachbooks_sphinx_grasple/translations/locales/el/LC_MESSAGES/grasple.mo
teachbooks_sphinx_grasple/translations/locales/el/LC_MESSAGES/grasple.po
teachbooks_sphinx_grasple/translations/locales/es/LC_MESSAGES/grasple.mo
teachbooks_sphinx_grasple/translations/locales/es/LC_MESSAGES/grasple.po
teachbooks_sphinx_grasple/translations/locales/fa/LC_MESSAGES/grasple.mo
teachbooks_sphinx_grasple/translations/locales/fa/LC_MESSAGES/grasple.po
teachbooks_sphinx_grasple/translations/locales/fr/LC_MESSAGES/grasple.mo
teachbooks_sphinx_grasple/translations/locales/fr/LC_MESSAGES/grasple.po
teachbooks_sphinx_grasple/translations/locales/he/LC_MESSAGES/grasple.mo
teachbooks_sphinx_grasple/translations/locales/he/LC_MESSAGES/grasple.po
teachbooks_sphinx_grasple/translations/locales/hi/LC_MESSAGES/grasple.mo
teachbooks_sphinx_grasple-1.3.0.dist-info/METADATA
teachbooks_sphinx_grasple-1.3.0.dist-info/WHEEL
teachbooks_sphinx_grasple-1.3.0.dist-info/licenses/LICENSE
teachbooks_sphinx_grasple-1.3.0.dist-info/RECORD
