Metadata-Version: 2.4
Name: teachbooks-sphinx-grasple
Version: 1.3.0
Summary: A Sphinx extension for inserting Grasple exercises.
Author-email: Daniel Balagué Guardia <d.balagueguardia@tudelft.nl>
License-File: LICENSE
Requires-Python: >=3.8
Requires-Dist: pypng
Requires-Dist: pyqrcode
Requires-Dist: sphinx-book-theme
Requires-Dist: sphinx>=4
Provides-Extra: all
Requires-Dist: beautifulsoup4; extra == 'all'
Requires-Dist: black; extra == 'all'
Requires-Dist: coverage; extra == 'all'
Requires-Dist: docutils<0.19,>=0.15; extra == 'all'
Requires-Dist: flake8<3.8.0,>=3.7.0; extra == 'all'
Requires-Dist: matplotlib; extra == 'all'
Requires-Dist: myst-nb~=0.17.1; extra == 'all'
Requires-Dist: pre-commit; extra == 'all'
Requires-Dist: pypng; extra == 'all'
Requires-Dist: pyqrcode; extra == 'all'
Requires-Dist: pytest-cov; extra == 'all'
Requires-Dist: pytest-regressions; extra == 'all'
Requires-Dist: pytest<4,>=3.6; extra == 'all'
Requires-Dist: sphinx-book-theme; extra == 'all'
Requires-Dist: sphinx-exercise; extra == 'all'
Requires-Dist: sphinx<6,>=4; extra == 'all'
Requires-Dist: texsoup; extra == 'all'
Provides-Extra: code-style
Requires-Dist: black; extra == 'code-style'
Requires-Dist: flake8<3.8.0,>=3.7.0; extra == 'code-style'
Requires-Dist: pre-commit; extra == 'code-style'
Provides-Extra: rtd
Requires-Dist: myst-nb~=0.17.1; extra == 'rtd'
Requires-Dist: sphinx-book-theme; extra == 'rtd'
Requires-Dist: sphinx-exercise; extra == 'rtd'
Requires-Dist: sphinx<6,>=4; extra == 'rtd'
Provides-Extra: testing
Requires-Dist: beautifulsoup4; extra == 'testing'
Requires-Dist: coverage; extra == 'testing'
Requires-Dist: docutils<0.19,>=0.15; extra == 'testing'
Requires-Dist: matplotlib; extra == 'testing'
Requires-Dist: myst-nb~=0.17.1; extra == 'testing'
Requires-Dist: pypng; extra == 'testing'
Requires-Dist: pyqrcode; extra == 'testing'
Requires-Dist: pytest-cov; extra == 'testing'
Requires-Dist: pytest-regressions; extra == 'testing'
Requires-Dist: pytest<4,>=3.6; extra == 'testing'
Requires-Dist: sphinx<6,>=4; extra == 'testing'
Requires-Dist: texsoup; extra == 'testing'
